s2h_api/__init__.py
s2h_api/api.py
s2h_api-1.2.dist-info/LICENSE
s2h_api-1.2.dist-info/METADATA
s2h_api-1.2.dist-info/WHEEL
s2h_api-1.2.dist-info/top_level.txt
s2h_api-1.2.dist-info/RECORD
