Metadata-Version: 2.1
Name: s2h-api
Version: 1.2
Summary: Simple api for s2h
Author-email: DataReset <datareset1000@gmail.com>
Project-URL: Homepage, https://github.com/DataReset/s2h-api
Project-URL: Bug Tracker, https://github.com/DataReset/s2h-api/issues
Classifier: Programming Language :: Python :: 3
Classifier: License :: OSI Approved :: MIT License
Classifier: Operating System :: OS Independent
Requires-Python: >=3.7
License-File: LICENSE
